pyatom_finance/__init__.py
pyatom_finance/collector.py
pyatom_finance/config.py
pyatom_finance/exceptions.py
pyatom_finance/requester.py
pyatom_finance/templates/get_better_consensuses.j2
pyatom_finance/templates/get_brokerage_actions.j2
pyatom_finance/templates/get_chart_interday.j2
pyatom_finance/templates/get_chart_intraday.j2
pyatom_finance/templates/get_financial_data.j2
pyatom_finance/templates/get_future_events.j2
pyatom_finance/templates/get_many_events.j2
pyatom_finance/templates/get_market_cap.j2
pyatom_finance/templates/get_near_events.j2
pyatom_finance/templates/get_news_feed.j2
pyatom_finance/templates/get_overview_data.j2
pyatom_finance/templates/get_past_events.j2
pyatom_finance/templates/get_period_guidance.j2
pyatom_finance/templates/get_relative_consensuses.j2
pyatom_finance/templates/get_symbol.j2
pyatom_finance-0.1.1.dist-info/WHEEL
pyatom_finance-0.1.1.dist-info/METADATA
pyatom_finance-0.1.1.dist-info/RECORD
